{
  "audioDuration": 3605,
  "audioUrl": "https://sphinx.acast.com/p/acast/s/un-bon-moment/e/6599c1b296596600156961a7/media.mp3",
  "date": "2024-01-29",
  "description": "Eddy vient cette semaine nous présenter son album Crash Coeur. Il échange avec Kyan et Navo sur la création de sa musique, son rapport au bonheur et l’envie de partager des textes. Frustré de ne pas manger de piment, il va tout faire pour gagner au Multiblindtest de Navo.",
  "guests": [
    "Eddy de Pretto"
  ],
  "guestsExcluded": [
    "invité",
    "Intervenant",
    "Eddie"
  ],
  "guestsParsed": [
    "Eddy de Pretto"
  ],
  "guid": "6599c1b296596600156961a7",
  "imageUrl": "https://assets.pippa.io/shows/61a754700fef25fd868debfb/1704575164782-9bae8c6b08a37ad664d8ae84e83a2415.jpeg",
  "number": 63,
  "sourceId": "un-bon-moment",
  "title": "avec Eddy de Pretto",
  "transcriptModel": "large-v3",
  "transcriptSource": "youtube",
  "transcriptStatus": "auto",
  "youtubeDuration": 3606,
  "youtubeTitle": "Un Bon Moment avec EDDY DE PRETTO",
  "youtubeUrl": "https://www.youtube.com/watch?v=5AzPR1uHpGg"
}
