{
  "sourceId": "un-bon-moment",
  "guid": "6929611768e521ed8d86a91b",
  "title": "Fabrice Éboué et Alexandra Roth musclent nos zygomatiques (Un Bon Moment, S5-E8)",
  "guests": [],
  "transcriptStatus": "auto",
  "date": "2025-12-01",
  "audioUrl": "https://sphinx.acast.com/p/acast/s/un-bon-moment/e/6929611768e521ed8d86a91b/media.mp3",
  "description": "<hr /><p style=\"color: grey; font-size: 0.75em;\"> Hébergé par Acast. Visitez <a href=\"https://acast.com/privacy\" rel=\"noopener noreferrer\" style=\"color: grey;\" target=\"_blank\">acast.com/privacy</a> pour plus d'informations.</p>",
  "youtubeUrl": "https://www.youtube.com/watch?v=TU59O6QoE3U",
  "audioDuration": 6389,
  "youtubeDuration": 6449,
  "youtubeTitle": "Fabrice Éboué et Alexandra Roth musclent nos zygomatiques (Un Bon Moment, S5-E8)",
  "season": 5,
  "number": 8
}
