{
  "sourceId": "un-bon-moment",
  "guid": "69872f249a20cfbf330ae7ab",
  "title": "Cyprien et Fanny La Panny multiplient les talents cachés (Un Bon Moment, S5-E18)",
  "guests": [],
  "transcriptStatus": "auto",
  "date": "2026-02-16",
  "audioUrl": "https://sphinx.acast.com/p/acast/s/un-bon-moment/e/69872f249a20cfbf330ae7ab/media.mp3",
  "description": "<hr /><p style=\"color: grey; font-size: 0.75em;\"> Hébergé par Acast. Visitez <a href=\"https://acast.com/privacy\" rel=\"noopener noreferrer\" style=\"color: grey;\" target=\"_blank\">acast.com/privacy</a> pour plus d'informations.</p>",
  "youtubeUrl": "https://www.youtube.com/watch?v=jLIpfGo8CGk",
  "audioDuration": 5460,
  "youtubeDuration": 5511,
  "youtubeTitle": "Cyprien et Fanny La Panny multiplient les talents cachés (Un Bon Moment, S5-E18)",
  "season": 5,
  "number": 18
}
