{
  "audioDuration": 3172,
  "audioUrl": "https://sphinx.acast.com/un-bon-moment/fadilycamara/media.mp3",
  "date": "2020-02-17",
  "description": "Avec l'humoriste et actrice FADILY CAMARA, Kyan et Navo partagent des idées et notes inédites et des anecdotes sur leurs débuts en tant qu'humoriste. Le pire moment de Kyan Khojandi en tant qu'humoriste pendant un mariage.\n\nJEUX : Johnny Depp // Les Notes Aléatoires",
  "guests": [
    "Fadily Camara"
  ],
  "guestsExcluded": [
    "l'humoriste FADILY CAMARA"
  ],
  "guestsParsed": [
    "l'humoriste FADILY CAMARA"
  ],
  "guid": "8099be2e-5c6d-4351-b52e-3b241b3dc229",
  "number": 4,
  "sourceId": "un-bon-moment",
  "title": "avec l'humoriste FADILY CAMARA",
  "transcriptModel": "large-v3-turbo",
  "transcriptSource": "youtube",
  "transcriptStatus": "auto",
  "youtubeDuration": 3258,
  "youtubeTitle": "UN BON MOMENT avec FADILY CAMARA",
  "youtubeUrl": "https://www.youtube.com/watch?v=MytQpfs9ndA"
}
