{
  "id": "un-bon-moment",
  "title": "Un Bon Moment",
  "tagline": "Les recos de Kyan & Navo",
  "recoPrefix": "ubm",
  "hosts": [
    "Kyan Khojandi",
    "Navo"
  ],
  "extractionAnchorPatterns": [
    "est-ce que tu as une reco",
    "ta reco",
    "qu'est-ce que tu nous recommandes"
  ],
  "youtubeTitleSuffixPatterns": [
    "un bon moment",
    "a good time"
  ],
  "avoidBrands": [
    "Amazon",
    "Bolloré"
  ],
  "siteColorAccent": "#ffd23f",
  "description": "C'est juste un bon moment avec des gens qu'on aime bien. Toutes les œuvres recommandées au fil des épisodes, rassemblées.",
  "rssUrl": "https://feeds.acast.com/public/shows/81a0b207-ecb9-4da6-b08a-64d929b67b6b",
  "youtubeChannel": "https://www.youtube.com/@KyanKhojandi",
  "website": "https://podcasts.apple.com/fr/podcast/un-bon-moment-avec-kyan-khojandi-et-navo/id1498725708",
  "theme": {
    "fontDisplay": "Reco Display",
    "fontBody": "Reco Body",
    "colors": {
      "bg": "#0e0e10",
      "surface": "#17171c",
      "text": "#f6f4ee",
      "muted": "#9a99a3",
      "accent": "#ffd23f",
      "accentText": "#0e0e10"
    }
  }
}